verilog/cpu15/ram_wb.v
module ram_wb(
	input CLK_WB,
	input[7:0] RAM_ADDR,
	input[15:0] RAM_IN,
	input RAM_WEN,
	output[15:0] RAM_0,
	output[15:0] RAM_1,
	output[15:0] RAM_2,
	output[15:0] RAM_3,
	output[15:0] RAM_4,
	output[15:0] RAM_5,
	output[15:0] RAM_6,
	output[15:0] RAM_7,
	output[15:0] IO64_OUT
);
	
	reg[15:0] RAM_0;
	reg[15:0] RAM_1;
	reg[15:0] RAM_2;
	reg[15:0] RAM_3;
	reg[15:0] RAM_4;
	reg[15:0] RAM_5;
	reg[15:0] RAM_6;
	reg[15:0] RAM_7;
	reg[15:0] IO64_OUT;

	always @(posedge CLK_WB) begin
		if (RAM_WEN == 1'b1) begin
			case (RAM_ADDR)
				8'b00000000: RAM_0 <= RAM_IN;
				8'b00000001: RAM_1 <= RAM_IN;
				8'b00000010: RAM_2 <= RAM_IN;
				8'b00000011: RAM_3 <= RAM_IN;
				8'b00000100: RAM_4 <= RAM_IN;
				8'b00000101: RAM_5 <= RAM_IN;
				8'b00000110: RAM_6 <= RAM_IN;
				8'b00000111: RAM_7 <= RAM_IN;
				8'b01000000: IO64_OUT <= RAM_IN;
				default: ; // nothing to do
			endcase
		end
	end
endmodule

verilog/cpu15/reg_wb.v
module reg_wb(
	input CLK_WB,
	input RESET_N,
	input[2:0] N_REG,
	input[15:0] REG_IN,
	input REG_WEN,
	output[15:0] REG_0,
	output[15:0] REG_1,
	output[15:0] REG_2,
	output[15:0] REG_3,
	output[15:0] REG_4,
	output[15:0] REG_5,
	output[15:0] REG_6,
	output[15:0] REG_7
);
	
	reg[15:0] REG_0;
	reg[15:0] REG_1;
	reg[15:0] REG_2;
	reg[15:0] REG_3;
	reg[15:0] REG_4;
	reg[15:0] REG_5;
	reg[15:0] REG_6;
	reg[15:0] REG_7;

	always @(posedge CLK_WB) begin
		if (RESET_N == 0) begin
			REG_0 <= 16'b0;
			REG_1 <= 16'b0;
			REG_2 <= 16'b0;
			REG_3 <= 16'b0;
			REG_4 <= 16'b0;
			REG_5 <= 16'b0;
			REG_6 <= 16'b0;
			REG_7 <= 16'b0;
		end
		else if (REG_WEN == 1) begin
			case (N_REG)
				3'b000: REG_0 <= REG_IN;
				3'b001: REG_1 <= REG_IN;
				3'b010: REG_2 <= REG_IN;
				3'b011: REG_3 <= REG_IN;
				3'b100: REG_4 <= REG_IN;
				3'b101: REG_5 <= REG_IN;
				3'b110: REG_6 <= REG_IN;
				3'b111: REG_7 <= REG_IN;
				default: ;// nothing to do
			endcase
		end
	end
endmodule

verilog/cpu15/exec.v
module exec(
    input CLK_EX,
    input RESET_N,
    input[3:0] OP_CODE,
    input[15:0] REG_A,
    input[15:0] REG_B,
    input[7:0] OP_DATA,
    input[15:0] RAM_OUT,
    output reg[7:0]	P_COUNT,
    output reg[15:0] REG_IN,
    output reg[15:0] RAM_IN,
    output reg REG_WEN,
    output reg RAM_WEN
);
    reg cmp_flag = 0;

    always @(posedge CLK_EX) begin
        if (RESET_N == 0) begin
            P_COUNT <= 0;
            cmp_flag <= 0;
        end
        else begin
            case (OP_CODE)
                4'b0000: // MOV
                begin
                    REG_IN <= REG_B;
                    REG_WEN <= 1;
                    RAM_WEN <= 0;
                    P_COUNT <= P_COUNT + 1;
                end
                4'b0001: // ADD
                begin
                    REG_IN <= REG_A + REG_B;
                    REG_WEN <= 1;
                    RAM_WEN <= 0;
                    P_COUNT <= P_COUNT + 1;
                end
                4'b0010: // SUB
                begin
                    REG_IN <= REG_A - REG_B;
                    REG_WEN <= 1;
                    RAM_WEN <= 0;
                    P_COUNT <= P_COUNT + 1;
                end
                4'b0011: // AND
                begin
                    REG_IN <= REG_A & REG_B;
                    REG_WEN <= 1;
                    RAM_WEN <= 0;
                    P_COUNT <= P_COUNT + 1;
                end
                4'b0100: // OR
                begin
                    REG_IN <= REG_A | REG_B;
                    REG_WEN <= 1;
                    RAM_WEN <= 0;
                    P_COUNT <= P_COUNT + 1;
                end
                4'b0101: // SL
                begin
                    REG_IN <= {REG_A[14:0], 1'b0};
                    REG_WEN <= 1;
                    RAM_WEN <= 0;
                    P_COUNT <= P_COUNT + 1;
                end
                4'b0110: // SR
                begin
                    REG_IN <= {1'b0, REG_A[15:1]};
                    REG_WEN <= 1;
                    RAM_WEN <= 0;
                    P_COUNT <= P_COUNT + 1;
                end
                4'b0111: // SRA
                begin
                    REG_IN <= {REG_A[15], REG_A[15:1]};
                    REG_WEN <= 1;
                    RAM_WEN <= 0;
                    P_COUNT <= P_COUNT + 1;
                end
                4'b1000: // LDL
                begin
                    REG_IN <= {REG_A[15:8], OP_DATA};
                    REG_WEN <= 1;
                    RAM_WEN <= 0;
                    P_COUNT <= P_COUNT + 1;
                end
                4'b1001: // LDH
                begin
                    REG_IN <= {OP_DATA, REG_A[7:0]};
                    REG_WEN <= 1;
                    RAM_WEN <= 0;
                    P_COUNT <= P_COUNT + 1;
                end
                4'b1010: // CMP
                begin
                    if (REG_A == REG_B) begin
                        cmp_flag <= 1;
                    end
                    else begin
                        cmp_flag <= 0;
                    end
                    REG_WEN <= 0;
                    RAM_WEN <= 0;
                    P_COUNT <= P_COUNT + 1;
                end
                4'b1011: // JE
                begin
                    if (cmp_flag == 1) begin
                        P_COUNT <= OP_DATA;
                    end
                    else begin
                        P_COUNT <= P_COUNT + 1;
                    end
                    REG_WEN <= 0;
                    RAM_WEN <= 0;
                end
                4'b1100: // JMP
                begin
                    REG_WEN <= 0;
                    RAM_WEN <= 0;
                    P_COUNT <= OP_DATA;
                end
                4'b1101: // LD
                begin
                    REG_IN <= RAM_OUT;
                    REG_WEN <= 1;
                    RAM_WEN <= 0;
                    P_COUNT <= P_COUNT + 1;
                end
                4'b1110: // ST
                begin
                    RAM_IN <= REG_A;
                    REG_WEN <= 0;
                    RAM_WEN <= 1;
                    P_COUNT <= P_COUNT + 1;
                end
                4'b1111: // HLT
                begin
                    REG_WEN <= 0;
                    RAM_WEN <= 0;
                end
                default: ;// nothing to do
            endcase
        end
    end
endmodule

verilog/cpu15/ram_dc.v
module ram_dc(
    input CLK_DC,
    input[7:0] RAM_AD_IN,
    input[15:0] RAM_0,
    input[15:0] RAM_1,
    input[15:0] RAM_2,
    input[15:0] RAM_3,
    input[15:0] RAM_4,
    input[15:0] RAM_5,
    input[15:0] RAM_6,
    input[15:0] RAM_7,
    input[15:0] IO65_IN,
    output[7:0] RAM_AD_OUT,
    output[15:0] RAM_OUT
);
    reg[15:0] RAM_OUT;

    always @(posedge CLK_DC) begin
        case (RAM_AD_IN)
            8'b00000000: RAM_OUT = RAM_0;
            8'b00000001: RAM_OUT = RAM_1;
            8'b00000010: RAM_OUT = RAM_2;
            8'b00000011: RAM_OUT = RAM_3;
            8'b00000100: RAM_OUT = RAM_4;
            8'b00000101: RAM_OUT = RAM_5;
            8'b00000110: RAM_OUT = RAM_6;
            8'b00000111: RAM_OUT = RAM_7;
            8'b01000001: RAM_OUT = IO65_IN;
            default: ; // nothing to do
        endcase
    end
    assign RAM_AD_OUT = RAM_AD_IN;
endmodule

verilog/cpu15/reg_dc.v
module reg_dc(
    input CLK_DC,
    input[2:0] N_REG_IN,
    input[15:0] REG_0,
    input[15:0] REG_1,
    input[15:0] REG_2,
    input[15:0] REG_3,
    input[15:0] REG_4,
    input[15:0] REG_5,
    input[15:0] REG_6,
    input[15:0] REG_7,
    output[2:0] N_REG_OUT,
    output[15:0] REG_OUT
);
    reg[2:0] N_REG_OUT;
    reg[15:0] REG_OUT;
    
    always @(posedge CLK_DC) begin
        case (N_REG_IN)
            3'b000: REG_OUT = REG_0;
            3'b001: REG_OUT = REG_1;
            3'b010: REG_OUT = REG_2;
            3'b011: REG_OUT = REG_3;
            3'b100: REG_OUT = REG_4;
            3'b101: REG_OUT = REG_5;
            3'b110: REG_OUT = REG_6;
            3'b111: REG_OUT = REG_7;
            default: ; // nothing to do
        endcase

        N_REG_OUT <= N_REG_IN;
    end
endmodule

verilog/cpu15/decode.v
module decode(
    input CLK_DC,
    input[14:0] PROM_OUT,
    output[3:0] OP_CODE,
    output[7:0] OP_DATA
);
    reg[3:0] OP_CODE;
    reg[7:0] OP_DATA;

    always @(posedge CLK_DC) begin
        OP_CODE <= PROM_OUT[14:11];
        OP_DATA <= PROM_OUT[7:0];
    end
endmodule

verilog/cpu15/fetch.v
module fetch(
    input CLK_FT,
    input[7:0] P_COUNT,
    output reg [14:0] PROM_OUT
);
    reg[14:0] mem[15:0];

    initial begin
        mem[0] = 15'b100100000000000;
        mem[1] = 15'b100000000000000;
        mem[2] = 15'b100100100000000;
        mem[3] = 15'b100000100000001;
        mem[4] = 15'b100101000000000;
        mem[5] = 15'b100001000000000;
        mem[6] = 15'b100101100000000;
        mem[7] = 15'b100001100001010;
        mem[8] = 15'b000101000100000;
        mem[9] = 15'b000100001000000;
        mem[10] = 15'b111000001000000;
        mem[11] = 15'b101001001100000;
        mem[12] = 15'b101100000001110;
        mem[13] = 15'b110000000001000;
        mem[14] = 15'b111100000000000;
        mem[15] = 15'b000000000000000;
    end

    always @(posedge CLK_FT) begin
        PROM_OUT <= mem[P_COUNT[3:0]];
    end
endmodule

verilog/cpu15/clk_gen.v
module clk_gen(
    input CLK,
    output CLK_FT,
    output CLK_DC,
    output CLK_EX,
    output CLK_WB
);
    reg[3:0] clk = 4'b0;
    reg[1:0] count = 2'b0;
    
    function[3:0] gen_clk;
        input[1:0] cnt;
        case (cnt)
            2'b00: gen_clk = 4'b0001;
            2'b01: gen_clk = 4'b0010;
            2'b10: gen_clk = 4'b0100;
            2'b11: gen_clk = 4'b1000;
            default: gen_clk = 4'bxxxx;
        endcase
    endfunction
    
    always @(posedge CLK) begin
        clk <= gen_clk(count);
        count <= count + 1;
    end

    assign CLK_FT = clk[0];
    assign CLK_DC = clk[1];
    assign CLK_EX = clk[2];
    assign CLK_WB = clk[3];

endmodule

verilog/cpu15/cpu15_sim.v
`timescale 1ns/1ns

module cpu15_sim;
    reg CLK = 1;
    reg RESET_N = 0;
    wire[15:0] IO65_IN;
    wire[15:0] IO64_OUT;
    wire clk_ft;
    wire clk_dc;
    wire clk_ex;
    wire clk_wb;
    wire[7:0] p_count;
    wire[14:0] prom_out;
    wire[3:0] op_code;
    wire[7:0] op_data;
    wire[2:0] n_reg_a;
    wire[2:0] n_reg_b;
    wire[15:0] reg_in;
    wire[15:0] reg_a;
    wire[15:0] reg_b;
    wire reg_wen;
    wire[15:0] reg_0;
    wire[15:0] reg_1;
    wire[15:0] reg_2;
    wire[15:0] reg_3;
    wire[15:0] reg_4;
    wire[15:0] reg_5;
    wire[15:0] reg_6;
    wire[15:0] reg_7;
    wire[7:0] ram_addr;
    wire[15:0] ram_in;
    wire[15:0] ram_out;
    wire ram_wen;
    wire[15:0] ram_0;
    wire[15:0] ram_1;
    wire[15:0] ram_2;
    wire[15:0] ram_3;
    wire[15:0] ram_4;
    wire[15:0] ram_5;
    wire[15:0] ram_6;
    wire[15:0] ram_7;

    clk_gen C1(
        .CLK(CLK),
        .CLK_FT(clk_ft),
        .CLK_DC(clk_dc),
        .CLK_EX(clk_ex),
        .CLK_WB(clk_wb)
    );

    fetch C2(
        .CLK_FT(clk_ft),
        .P_COUNT(p_count),
        .PROM_OUT(prom_out)
    );

    decode C3(
        .CLK_DC(clk_dc),
        .PROM_OUT(prom_out),
        .OP_CODE(op_code),
        .OP_DATA(op_data)
    );

    reg_dc C4(
        .CLK_DC(clk_dc),
        .N_REG_IN(prom_out[10:8]),
        .REG_0(reg_0),
        .REG_1(reg_1),
        .REG_2(reg_2),
        .REG_3(reg_3),
        .REG_4(reg_4),
        .REG_5(reg_5),
        .REG_6(reg_6),
        .REG_7(reg_7),
        .N_REG_OUT(n_reg_a),
        .REG_OUT(reg_a)
    );

    reg_dc C5(
        .CLK_DC(clk_dc),
        .N_REG_IN(prom_out[7:5]),
        .REG_0(reg_0),
        .REG_1(reg_1),
        .REG_2(reg_2),
        .REG_3(reg_3),
        .REG_4(reg_4),
        .REG_5(reg_5),
        .REG_6(reg_6),
        .REG_7(reg_7),
        .N_REG_OUT(n_reg_b),
        .REG_OUT(reg_b)
    );

    ram_dc C6(
        .CLK_DC(clk_dc),
        .RAM_AD_IN(prom_out[7:0]),
        .RAM_0(ram_0),
        .RAM_1(ram_1),
        .RAM_2(ram_2),
        .RAM_3(ram_3),
        .RAM_4(ram_4),
        .RAM_5(ram_5),
        .RAM_6(ram_6),
        .RAM_7(ram_7),
        .IO65_IN(IO65_IN),
        .RAM_AD_OUT(ram_addr),
        .RAM_OUT(ram_out)
    );

    exec C7(
        .CLK_EX(clk_ex),
        .RESET_N(RESET_N),
        .OP_CODE(op_code),
        .REG_A(reg_a),
        .REG_B(reg_b),
        .OP_DATA(op_data),
        .RAM_OUT(ram_out),
        .P_COUNT(p_count),
        .REG_IN(reg_in),
        .RAM_IN(ram_in),
        .REG_WEN(reg_wen),
        .RAM_WEN(ram_wen)
    );

    reg_wb C8(
        .CLK_WB(clk_wb),
        .RESET_N(RESET_N),
        .N_REG(n_reg_a),
        .REG_IN(reg_in),
        .REG_WEN(reg_wen),
        .REG_0(reg_0),
        .REG_1(reg_1),
        .REG_2(reg_2),
        .REG_3(reg_3),
        .REG_4(reg_4),
        .REG_5(reg_5),
        .REG_6(reg_6),
        .REG_7(reg_7)
    );

    ram_wb C9(
        .CLK_WB(clk_wb),
        .RAM_ADDR(ram_addr),
        .RAM_IN(ram_in),
        .RAM_WEN(ram_wen),
        .RAM_0(ram_0),
        .RAM_1(ram_1),
        .RAM_2(ram_2),
        .RAM_3(ram_3),
        .RAM_4(ram_4),
        .RAM_5(ram_5),
        .RAM_6(ram_6),
        .RAM_7(ram_7),
        .IO64_OUT(IO64_OUT)
    );

	parameter T = 20;
	
	always #(T/2)
		CLK = ~CLK;

	initial begin
		#(T*5) RESET_N = 1;
		#(T*300) $finish;
	end
	
	initial begin
		$dumpfile("cpu15_sim.vcd");
		$dumpvars(0, cpu15_sim);
	end
endmodule

verilog/cpu15/cpu15_sim.vcd
$date
	Tue Jul 11 09:31:32 2023
$end
$version
	Icarus Verilog
$end
$timescale
	1ns
$end
$scope module cpu15_sim $end
$var wire 16 ! IO65_IN [15:0] $end
$var wire 1 " reg_wen $end
$var wire 16 # reg_in [15:0] $end
$var wire 16 $ reg_b [15:0] $end
$var wire 16 % reg_a [15:0] $end
$var wire 16 & reg_7 [15:0] $end
$var wire 16 ' reg_6 [15:0] $end
$var wire 16 ( reg_5 [15:0] $end
$var wire 16 ) reg_4 [15:0] $end
$var wire 16 * reg_3 [15:0] $end
$var wire 16 + reg_2 [15:0] $end
$var wire 16 , reg_1 [15:0] $end
$var wire 16 - reg_0 [15:0] $end
$var wire 1 . ram_wen $end
$var wire 16 / ram_out [15:0] $end
$var wire 16 0 ram_in [15:0] $end
$var wire 8 1 ram_addr [7:0] $end
$var wire 16 2 ram_7 [15:0] $end
$var wire 16 3 ram_6 [15:0] $end
$var wire 16 4 ram_5 [15:0] $end
$var wire 16 5 ram_4 [15:0] $end
$var wire 16 6 ram_3 [15:0] $end
$var wire 16 7 ram_2 [15:0] $end
$var wire 16 8 ram_1 [15:0] $end
$var wire 16 9 ram_0 [15:0] $end
$var wire 15 : prom_out [14:0] $end
$var wire 8 ; p_count [7:0] $end
$var wire 8 < op_data [7:0] $end
$var wire 4 = op_code [3:0] $end
$var wire 3 > n_reg_b [2:0] $end
$var wire 3 ? n_reg_a [2:0] $end
$var wire 1 @ clk_wb $end
$var wire 1 A clk_ft $end
$var wire 1 B clk_ex $end
$var wire 1 C clk_dc $end
$var wire 16 D IO64_OUT [15:0] $end
$var reg 1 E CLK $end
$var reg 1 F RESET_N $end
$scope module C1 $end
$var wire 1 E CLK $end
$var wire 1 @ CLK_WB $end
$var wire 1 A CLK_FT $end
$var wire 1 B CLK_EX $end
$var wire 1 C CLK_DC $end
$var reg 4 G clk [3:0] $end
$var reg 2 H count [1:0] $end
$upscope $end
$scope module C2 $end
$var wire 1 A CLK_FT $end
$var wire 8 I P_COUNT [7:0] $end
$var reg 15 J PROM_OUT [14:0] $end
$upscope $end
$scope module C3 $end
$var wire 1 C CLK_DC $end
$var wire 15 K PROM_OUT [14:0] $end
$var reg 4 L OP_CODE [3:0] $end
$var reg 8 M OP_DATA [7:0] $end
$upscope $end
$scope module C4 $end
$var wire 1 C CLK_DC $end
$var wire 3 N N_REG_IN [2:0] $end
$var wire 16 O REG_7 [15:0] $end
$var wire 16 P REG_6 [15:0] $end
$var wire 16 Q REG_5 [15:0] $end
$var wire 16 R REG_4 [15:0] $end
$var wire 16 S REG_3 [15:0] $end
$var wire 16 T REG_2 [15:0] $end
$var wire 16 U REG_1 [15:0] $end
$var wire 16 V REG_0 [15:0] $end
$var reg 3 W N_REG_OUT [2:0] $end
$var reg 16 X REG_OUT [15:0] $end
$upscope $end
$scope module C5 $end
$var wire 1 C CLK_DC $end
$var wire 3 Y N_REG_IN [2:0] $end
$var wire 16 Z REG_7 [15:0] $end
$var wire 16 [ REG_6 [15:0] $end
$var wire 16 \ REG_5 [15:0] $end
$var wire 16 ] REG_4 [15:0] $end
$var wire 16 ^ REG_3 [15:0] $end
$var wire 16 _ REG_2 [15:0] $end
$var wire 16 ` REG_1 [15:0] $end
$var wire 16 a REG_0 [15:0] $end
$var reg 3 b N_REG_OUT [2:0] $end
$var reg 16 c REG_OUT [15:0] $end
$upscope $end
$scope module C6 $end
$var wire 1 C CLK_DC $end
$var wire 16 d IO65_IN [15:0] $end
$var wire 8 e RAM_AD_IN [7:0] $end
$var wire 8 f RAM_AD_OUT [7:0] $end
$var wire 16 g RAM_7 [15:0] $end
$var wire 16 h RAM_6 [15:0] $end
$var wire 16 i RAM_5 [15:0] $end
$var wire 16 j RAM_4 [15:0] $end
$var wire 16 k RAM_3 [15:0] $end
$var wire 16 l RAM_2 [15:0] $end
$var wire 16 m RAM_1 [15:0] $end
$var wire 16 n RAM_0 [15:0] $end
$var reg 16 o RAM_OUT [15:0] $end
$upscope $end
$scope module C7 $end
$var wire 1 B CLK_EX $end
$var wire 4 p OP_CODE [3:0] $end
$var wire 8 q OP_DATA [7:0] $end
$var wire 16 r RAM_OUT [15:0] $end
$var wire 16 s REG_A [15:0] $end
$var wire 16 t REG_B [15:0] $end
$var wire 1 F RESET_N $end
$var reg 8 u P_COUNT [7:0] $end
$var reg 16 v RAM_IN [15:0] $end
$var reg 1 . RAM_WEN $end
$var reg 16 w REG_IN [15:0] $end
$var reg 1 " REG_WEN $end
$var reg 1 x cmp_flag $end
$upscope $end
$scope module C8 $end
$var wire 1 @ CLK_WB $end
$var wire 3 y N_REG [2:0] $end
$var wire 16 z REG_IN [15:0] $end
$var wire 1 " REG_WEN $end
$var wire 1 F RESET_N $end
$var reg 16 { REG_0 [15:0] $end
$var reg 16 | REG_1 [15:0] $end
$var reg 16 } REG_2 [15:0] $end
$var reg 16 ~ REG_3 [15:0] $end
$var reg 16 !" REG_4 [15:0] $end
$var reg 16 "" REG_5 [15:0] $end
$var reg 16 #" REG_6 [15:0] $end
$var reg 16 $" REG_7 [15:0] $end
$upscope $end
$scope module C9 $end
$var wire 1 @ CLK_WB $end
$var wire 8 %" RAM_ADDR [7:0] $end
$var wire 16 &" RAM_IN [15:0] $end
$var wire 1 . RAM_WEN $end
$var reg 16 '" IO64_OUT [15:0] $end
$var reg 16 (" RAM_0 [15:0] $end
$var reg 16 )" RAM_1 [15:0] $end
$var reg 16 *" RAM_2 [15:0] $end
$var reg 16 +" RAM_3 [15:0] $end
$var reg 16 ," RAM_4 [15:0] $end
$var reg 16 -" RAM_5 [15:0] $end
$var reg 16 ." RAM_6 [15:0] $end
$var reg 16 /" RAM_7 [15:0] $end
$upscope $end
$upscope $end
$enddefinitions $end
#0
$dumpvars
bx /"
bx ."
bx -"
bx ,"
bx +"
bx *"
bx )"
bx ("
bx '"
bx &"
b0 %"
bx $"
bx #"
bx ""
bx !"
bx ~
bx }
bx |
bx {
bx z
bx y
0x
bx w
bx v
b0 u
bx t
bx s
bx r
bx q
bx p
bx o
bx n
bx m
bx l
bx k
bx j
bx i
bx h
bx g
b0 f
b0 e
bz d
bx c
bx b
bx a
bx `
bx _
bx ^
bx ]
bx \
bx [
bx Z
b0 Y
bx X
bx W
bx V
bx U
bx T
bx S
bx R
bx Q
bx P
bx O
b0 N
bx M
bx L
b100100000000000 K
b100100000000000 J
b0 I
b1 H
b1 G
0F
1E
bx D
0C
0B
1A
0@
bx ?
bx >
bx =
bx <
b0 ;
b100100000000000 :
bx 9
bx 8
bx 7
bx 6
bx 5
bx 4
bx 3
bx 2
b0 1
bx 0
bx /
x.
bx -
bx ,
bx +
bx *
bx )
bx (
bx '
bx &
bx %
bx $
bx #
x"
bz !
$end
#10
0E
#20
b0 <
b0 M
b0 q
b1001 =
b1001 L
b1001 p
b0 ?
b0 W
b0 y
b0 >
b0 b
b10 H
0A
1C
b10 G
1E
#30
0E
#40
b11 H
0C
1B
b100 G
1E
#50
0E
#60
b0 &
b0 O
b0 Z
b0 $"
b0 '
b0 P
b0 [
b0 #"
b0 (
b0 Q
b0 \
b0 ""
b0 )
b0 R
b0 ]
b0 !"
b0 *
b0 S
b0 ^
b0 ~
b0 +
b0 T
b0 _
b0 }
b0 ,
b0 U
b0 `
b0 |
b0 -
b0 V
b0 a
b0 {
b0 H
0B
1@
b1000 G
1E
#70
0E
#80
b1 H
1A
0@
b1 G
1E
#90
0E
#100
b10 H
b0 $
b0 c
b0 t
b0 %
b0 X
b0 s
0A
1C
b10 G
1E
1F
#110
0E
#120
b1 ;
b1 I
b1 u
0.
1"
b0 #
b0 w
b0 z
b11 H
0C
1B
b100 G
1E
#130
0E
#140
b0 H
0B
1@
b1000 G
1E
#150
0E
#160
b1 H
b100000000000000 :
b100000000000000 J
b100000000000000 K
1A
0@
b1 G
1E
#170
0E
#180
b1000 =
b1000 L
b1000 p
b10 H
0A
1C
b10 G
1E
#190
0E
#200
b10 ;
b10 I
b10 u
b11 H
0C
1B
b100 G
1E
#210
0E
#220
b0 H
0B
1@
b1000 G
1E
#230
0E
#240
b1 H
b1 N
b100100100000000 :
b100100100000000 J
b100100100000000 K
1A
0@
b1 G
1E
#250
0E
#260
b1 ?
b1 W
b1 y
b1001 =
b1001 L
b1001 p
b10 H
0A
1C
b10 G
1E
#270
0E
#280
b11 ;
b11 I
b11 u
b11 H
0C
1B
b100 G
1E
#290
0E
#300
b0 H
0B
1@
b1000 G
1E
#310
0E
#320
b1 H
b1 1
b1 f
b1 %"
b1 e
b100000100000001 :
b100000100000001 J
b100000100000001 K
1A
0@
b1 G
1E
#330
0E
#340
b1 <
b1 M
b1 q
b1000 =
b1000 L
b1000 p
b10 H
0A
1C
b10 G
1E
#350
0E
#360
b100 ;
b100 I
b100 u
b1 #
b1 w
b1 z
b11 H
0C
1B
b100 G
1E
#370
0E
#380
b1 ,
b1 U
b1 `
b1 |
b0 H
0B
1@
b1000 G
1E
#390
0E
#400
b1 H
b0 1
b0 f
b0 %"
b0 e
b10 N
b100101000000000 :
b100101000000000 J
b100101000000000 K
1A
0@
b1 G
1E
#410
0E
#420
b10 ?
b10 W
b10 y
b0 <
b0 M
b0 q
b1001 =
b1001 L
b1001 p
b10 H
0A
1C
b10 G
1E
#430
0E
#440
b101 ;
b101 I
b101 u
b0 #
b0 w
b0 z
b11 H
0C
1B
b100 G
1E
#450
0E
#460
b0 H
0B
1@
b1000 G
1E
#470
0E
#480
b1 H
b100001000000000 :
b100001000000000 J
b100001000000000 K
1A
0@
b1 G
1E
#490
0E
#500
b1000 =
b1000 L
b1000 p
b10 H
0A
1C
b10 G
1E
#510
0E
#520
b110 ;
b110 I
b110 u
b11 H
0C
1B
b100 G
1E
#530
0E
#540
b0 H
0B
1@
b1000 G
1E
#550
0E
#560
b1 H
b11 N
b100101100000000 :
b100101100000000 J
b100101100000000 K
1A
0@
b1 G
1E
#570
0E
#580
b11 ?
b11 W
b11 y
b1001 =
b1001 L
b1001 p
b10 H
0A
1C
b10 G
1E
#590
0E
#600
b111 ;
b111 I
b111 u
b11 H
0C
1B
b100 G
1E
#610
0E
#620
b0 H
0B
1@
b1000 G
1E
#630
0E
#640
b1 H
b1010 1
b1010 f
b1010 %"
b1010 e
b100001100001010 :
b100001100001010 J
b100001100001010 K
1A
0@
b1 G
1E
#650
0E
#660
b1010 <
b1010 M
b1010 q
b1000 =
b1000 L
b1000 p
b10 H
0A
1C
b10 G
1E
#670
0E
#680
b1000 ;
b1000 I
b1000 u
b1010 #
b1010 w
b1010 z
b11 H
0C
1B
b100 G
1E
#690
0E
#700
b1010 *
b1010 S
b1010 ^
b1010 ~
b0 H
0B
1@
b1000 G
1E
#710
0E
#720
b1 H
b100000 1
b100000 f
b100000 %"
b100000 e
b1 Y
b10 N
b101000100000 :
b101000100000 J
b101000100000 K
1A
0@
b1 G
1E
#730
0E
#740
b1 >
b1 b
b10 ?
b10 W
b10 y
b100000 <
b100000 M
b100000 q
b1 =
b1 L
b1 p
b10 H
b1 $
b1 c
b1 t
0A
1C
b10 G
1E
#750
0E
#760
b1001 ;
b1001 I
b1001 u
b1 #
b1 w
b1 z
b11 H
0C
1B
b100 G
1E
#770
0E
#780
b1 +
b1 T
b1 _
b1 }
b0 H
0B
1@
b1000 G
1E
#790
0E
#800
b1 H
b1000000 1
b1000000 f
b1000000 %"
b1000000 e
b10 Y
b0 N
b100001000000 :
b100001000000 J
b100001000000 K
1A
0@
b1 G
1E
#810
0E
#820
b1000000 <
b1000000 M
b1000000 q
b0 ?
b0 W
b0 y
b10 >
b10 b
b10 H
0A
1C
b10 G
1E
#830
0E
#840
b1010 ;
b1010 I
b1010 u
b11 H
0C
1B
b100 G
1E
#850
0E
#860
b1 -
b1 V
b1 a
b1 {
b0 H
0B
1@
b1000 G
1E
#870
0E
#880
b1 H
b111000001000000 :
b111000001000000 J
b111000001000000 K
1A
0@
b1 G
1E
#890
0E
#900
b1110 =
b1110 L
b1110 p
b10 H
b1 %
b1 X
b1 s
0A
1C
b10 G
1E
#910
0E
#920
b1011 ;
b1011 I
b1011 u
1.
0"
b1 0
b1 v
b1 &"
b11 H
0C
1B
b100 G
1E
#930
0E
#940
b1 D
b1 '"
b0 H
0B
1@
b1000 G
1E
#950
0E
#960
b1 H
b1100000 1
b1100000 f
b1100000 %"
b1100000 e
b11 Y
b10 N
b101001001100000 :
b101001001100000 J
b101001001100000 K
1A
0@
b1 G
1E
#970
0E
#980
b1100000 <
b1100000 M
b1100000 q
b1010 =
b1010 L
b1010 p
b10 ?
b10 W
b10 y
b11 >
b11 b
b10 H
b1010 $
b1010 c
b1010 t
0A
1C
b10 G
1E
#990
0E
#1000
b1100 ;
b1100 I
b1100 u
0.
b11 H
0C
1B
b100 G
1E
#1010
0E
#1020
b0 H
0B
1@
b1000 G
1E
#1030
0E
#1040
b1 H
b1110 1
b1110 f
b1110 %"
b1110 e
b0 Y
b0 N
b101100000001110 :
b101100000001110 J
b101100000001110 K
1A
0@
b1 G
1E
#1050
0E
#1060
b0 >
b0 b
b0 ?
b0 W
b0 y
b1110 <
b1110 M
b1110 q
b1011 =
b1011 L
b1011 p
b10 H
b1 $
b1 c
b1 t
0A
1C
b10 G
1E
#1070
0E
#1080
b1101 ;
b1101 I
b1101 u
b11 H
0C
1B
b100 G
1E
#1090
0E
#1100
b0 H
0B
1@
b1000 G
1E
#1110
0E
#1120
b1 H
b1000 1
b1000 f
b1000 %"
b1000 e
b110000000001000 :
b110000000001000 J
b110000000001000 K
1A
0@
b1 G
1E
#1130
0E
#1140
b1000 <
b1000 M
b1000 q
b1100 =
b1100 L
b1100 p
b10 H
0A
1C
b10 G
1E
#1150
0E
#1160
b1000 ;
b1000 I
b1000 u
b11 H
0C
1B
b100 G
1E
#1170
0E
#1180
b0 H
0B
1@
b1000 G
1E
#1190
0E
#1200
b1 H
b100000 1
b100000 f
b100000 %"
b100000 e
b1 Y
b10 N
b101000100000 :
b101000100000 J
b101000100000 K
1A
0@
b1 G
1E
#1210
0E
#1220
b1 >
b1 b
b10 ?
b10 W
b10 y
b100000 <
b100000 M
b100000 q
b1 =
b1 L
b1 p
b10 H
0A
1C
b10 G
1E
#1230
0E
#1240
b1001 ;
b1001 I
b1001 u
1"
b10 #
b10 w
b10 z
b11 H
0C
1B
b100 G
1E
#1250
0E
#1260
b10 +
b10 T
b10 _
b10 }
b0 H
0B
1@
b1000 G
1E
#1270
0E
#1280
b1 H
b1000000 1
b1000000 f
b1000000 %"
b1000000 e
b10 Y
b0 N
b100001000000 :
b100001000000 J
b100001000000 K
1A
0@
b1 G
1E
#1290
0E
#1300
b1000000 <
b1000000 M
b1000000 q
b0 ?
b0 W
b0 y
b10 >
b10 b
b10 H
b10 $
b10 c
b10 t
0A
1C
b10 G
1E
#1310
0E
#1320
b1010 ;
b1010 I
b1010 u
b11 #
b11 w
b11 z
b11 H
0C
1B
b100 G
1E
#1330
0E
#1340
b11 -
b11 V
b11 a
b11 {
b0 H
0B
1@
b1000 G
1E
#1350
0E
#1360
b1 H
b111000001000000 :
b111000001000000 J
b111000001000000 K
1A
0@
b1 G
1E
#1370
0E
#1380
b1110 =
b1110 L
b1110 p
b10 H
b11 %
b11 X
b11 s
0A
1C
b10 G
1E
#1390
0E
#1400
b1011 ;
b1011 I
b1011 u
1.
0"
b11 0
b11 v
b11 &"
b11 H
0C
1B
b100 G
1E
#1410
0E
#1420
b11 D
b11 '"
b0 H
0B
1@
b1000 G
1E
#1430
0E
#1440
b1 H
b1100000 1
b1100000 f
b1100000 %"
b1100000 e
b11 Y
b10 N
b101001001100000 :
b101001001100000 J
b101001001100000 K
1A
0@
b1 G
1E
